[
    {
        "open": 1086.9,
        "high": 1155.9,
        "low": 1075.5,
        "close": 1132.2,
        "date": 1750377600,
        "volume": 732507
    },
    {
        "open": 1130.0,
        "high": 1130.0,
        "low": 1091.5,
        "close": 1097.6,
        "date": 1750636800,
        "volume": 286549
    },
    {
        "open": 1104.0,
        "high": 1112.8,
        "low": 1089.2,
        "close": 1093.2,
        "date": 1750723200,
        "volume": 176575
    },
    {
        "open": 1090.0,
        "high": 1103.1,
        "low": 1082.0,
        "close": 1086.4,
        "date": 1750809600,
        "volume": 190904
    },
    {
        "open": 1083.0,
        "high": 1108.8,
        "low": 1059.0,
        "close": 1105.7,
        "date": 1750896000,
        "volume": 567403
    }
]