[
    {
        "open": 312.2,
        "high": 316.0,
        "low": 309.8,
        "close": 312.85,
        "date": 1750377600,
        "volume": 24642
    },
    {
        "open": 314.45,
        "high": 317.7,
        "low": 309.1,
        "close": 316.6,
        "date": 1750636800,
        "volume": 33040
    },
    {
        "open": 318.2,
        "high": 325.0,
        "low": 316.5,
        "close": 322.45,
        "date": 1750723200,
        "volume": 70950
    },
    {
        "open": 323.9,
        "high": 327.3,
        "low": 320.3,
        "close": 324.6,
        "date": 1750809600,
        "volume": 54021
    }
]