[
    {
        "open": 105.85,
        "high": 105.85,
        "low": 100.4,
        "close": 101.38,
        "date": 1750377600,
        "volume": 20912
    },
    {
        "open": 102.0,
        "high": 104.95,
        "low": 102.0,
        "close": 104.03,
        "date": 1750636800,
        "volume": 8723
    },
    {
        "open": 106.8,
        "high": 106.8,
        "low": 103.8,
        "close": 104.57,
        "date": 1750723200,
        "volume": 7663
    },
    {
        "open": 105.69,
        "high": 106.2,
        "low": 104.0,
        "close": 105.75,
        "date": 1750809600,
        "volume": 11245
    }
]