[
    {
        "open": 744.25,
        "high": 754.0,
        "low": 730.0,
        "close": 737.25,
        "date": 1750377600,
        "volume": 1229
    },
    {
        "open": 730.0,
        "high": 742.0,
        "low": 702.4,
        "close": 740.05,
        "date": 1750636800,
        "volume": 1703
    },
    {
        "open": 740.05,
        "high": 755.0,
        "low": 703.5,
        "close": 728.0,
        "date": 1750723200,
        "volume": 3746
    },
    {
        "open": 715.0,
        "high": 728.0,
        "low": 701.0,
        "close": 724.8,
        "date": 1750809600,
        "volume": 6399
    }
]